MANIFEST.in
README.rst
requirements.txt
setup.py
code_checker.egg-info/PKG-INFO
code_checker.egg-info/SOURCES.txt
code_checker.egg-info/dependency_links.txt
code_checker.egg-info/entry_points.txt
code_checker.egg-info/requires.txt
code_checker.egg-info/top_level.txt
codechecker/__init__.py
codechecker/checkers_spec.py
codechecker/git.py
codechecker/result_creators.py
codechecker/worker.py
codechecker/checker/__init__.py
codechecker/checker/builder.py
codechecker/checker/task.py
codechecker/scripts/__init__.py
codechecker/scripts/hooksetup.py
codechecker/scripts/runner.py