Metadata-Version: 1.1
Name: code-checker
Version: 0.2.1.post1
Summary: Run pre-commit code checkers
Home-page: https://github.com/droslaw/GitHooks
Author: Sławek Dróżdż
Author-email: droslaw@gmail.com
License: MIT
Platform: UNKNOWN
Classifier: Development Status :: 2 - Pre-Alpha
Classifier: Environment :: Console
Classifier: Intended Audience :: Developers
Classifier: License :: OSI Approved :: MIT License
Classifier: Natural Language :: English
Classifier: Operating System :: POSIX :: Linux
Classifier: Programming Language :: Python :: 3
Classifier: Programming Language :: Python :: Implementation :: CPython
Classifier: Topic :: Software Development :: Quality Assurance
